CHANGELOG.txt
MANIFEST.in
README.rst
setup.cfg
setup.py
pyliftover/__init__.py
pyliftover/chainfile.py
pyliftover/intervaltree.py
pyliftover/liftover.py
pyliftover.egg-info/PKG-INFO
pyliftover.egg-info/SOURCES.txt
pyliftover.egg-info/dependency_links.txt
pyliftover.egg-info/top_level.txt
pyliftover.egg-info/zip-safe