Metadata-Version: 1.1
Name: pyliftover
Version: 0.3
Summary: Pure-python implementation of UCSC ``liftOver`` genome coordinate conversion.
Home-page: https://github.com/konstantint/pyliftover
Author: Konstantin Tretyakov
Author-email: kt@ut.ee
License: MIT
Keywords: bioinformatics liftover genome-analysis
Platform: Platform Independent
Classifier: Development Status :: 3 - Alpha
Classifier: Intended Audience :: Science/Research
Classifier: License :: OSI Approved :: MIT License
Classifier: Operating System :: OS Independent
Classifier: Programming Language :: Python :: 2
Classifier: Programming Language :: Python :: 3
Classifier: Topic :: Scientific/Engineering :: Bio-Informatics
